palonsoOscars/acceso_oscars.py
palonsoOscars/settings.py
palonsooscars-0.0.3.dist-info/METADATA
palonsooscars-0.0.3.dist-info/WHEEL
palonsooscars-0.0.3.dist-info/RECORD
