Metadata-Version: 2.1
Name: palonsoOscars
Version: 0.0.3
Summary: My customized ORM on Sales
Project-URL: Homepage, https://github.com/Palons0/oscars
Project-URL: Bug Tracker, https://github.com/Palons0/oscars/issues
Author-email: palonso <pablo.alonso@gmail.com>
Classifier: License :: OSI Approved :: MIT License
Classifier: Operating System :: OS Independent
Classifier: Programming Language :: Python :: 3
Requires-Python: >=3.9
